gpt_repository_loader/.gptignore
gpt_repository_loader/__init__.py
gpt_repository_loader/cli.py
gpt_repository_loader/gpt_repository_loader.py
gptrepo-1.0.3.dist-info/LICENSE
gptrepo-1.0.3.dist-info/METADATA
gptrepo-1.0.3.dist-info/WHEEL
gptrepo-1.0.3.dist-info/entry_points.txt
gptrepo-1.0.3.dist-info/top_level.txt
gptrepo-1.0.3.dist-info/RECORD
