Metadata-Version: 2.1
Name: gptrepo
Version: 1.0.3
Summary: gpt repository loader
Home-page: https://github.com/zackees/gptrepo
Maintainer: Zachary Vorhies
License: BSD 3-Clause License
Keywords: template-python-cmd
Classifier: Programming Language :: Python :: 3
Requires-Python: >=3.7
License-File: LICENSE
Requires-Dist: pyperclip
